gjr_garch_x/__init__.py
gjr_garch_x/py.typed
gjr_garch_x-0.1.0.dist-info/METADATA
gjr_garch_x-0.1.0.dist-info/WHEEL
gjr_garch_x-0.1.0.dist-info/licenses/LICENSE
gjr_garch_x-0.1.0.dist-info/RECORD
