Metadata-Version: 2.4
Name: gjr-garch-x
Version: 0.1.0
Summary: GJR-GARCH models with exogenous regressors in the variance equation
Project-URL: Homepage, https://github.com/studiofarzulla/gjr-garch-x
Project-URL: Documentation, https://github.com/studiofarzulla/gjr-garch-x#readme
Project-URL: Repository, https://github.com/studiofarzulla/gjr-garch-x
Project-URL: Issues, https://github.com/studiofarzulla/gjr-garch-x/issues
Project-URL: Changelog, https://github.com/studiofarzulla/gjr-garch-x/blob/main/CHANGELOG.md
Author-email: Murad Farzulla <murad@farzulla.org>
Maintainer-email: Murad Farzulla <murad@farzulla.org>
License: MIT
License-File: LICENSE
Keywords: cryptocurrency,econometrics,event-study,finance,garch,gjr-garch,glosten-jagannathan-runkle,heteroskedasticity,time-series,variance-modeling,volatility
Classifier: Development Status :: 4 - Beta
Classifier: Intended Audience :: Financial and Insurance Industry
Classifier: Intended Audience :: Science/Research
Classifier: License :: OSI Approved :: MIT License
Classifier: Operating System :: OS Independent
Classifier: Programming Language :: Python :: 3
Classifier: Programming Language :: Python :: 3.9
Classifier: Programming Language :: Python :: 3.10
Classifier: Programming Language :: Python :: 3.11
Classifier: Programming Language :: Python :: 3.12
Classifier: Programming Language :: Python :: 3.13
Classifier: Topic :: Office/Business :: Financial :: Investment
Classifier: Topic :: Scientific/Engineering :: Mathematics
Classifier: Typing :: Typed
Requires-Python: >=3.9
Requires-Dist: numpy>=1.21.0
Requires-Dist: pandas>=1.3.0
Requires-Dist: scipy>=1.7.0
Provides-Extra: dev
Requires-Dist: black>=23.0.0; extra == 'dev'
Requires-Dist: mypy>=1.0.0; extra == 'dev'
Requires-Dist: pandas-stubs>=2.0.0; extra == 'dev'
Requires-Dist: pytest-cov>=4.0.0; extra == 'dev'
Requires-Dist: pytest>=7.0.0; extra == 'dev'
Requires-Dist: ruff>=0.1.0; extra == 'dev'
Provides-Extra: docs
Requires-Dist: myst-parser>=1.0.0; extra == 'docs'
Requires-Dist: sphinx-rtd-theme>=1.0.0; extra == 'docs'
Requires-Dist: sphinx>=6.0.0; extra == 'docs'
